bond/__init__.py
bond/agent.py
bond/utils.py
bond/server/__init__.py
bond/server/_app.py
bond/server/_routes.py
bond/server/_session.py
bond/server/_types.py
bond/tools/__init__.py
bond/tools/_composite.py
bond/tools/github/__init__.py
bond/tools/github/_adapter.py
bond/tools/github/_exceptions.py
bond/tools/github/_models.py
bond/tools/github/_protocols.py
bond/tools/github/_types.py
bond/tools/github/tools.py
bond/tools/githunter/__init__.py
bond/tools/githunter/_adapter.py
bond/tools/githunter/_exceptions.py
bond/tools/githunter/_models.py
bond/tools/githunter/_protocols.py
bond/tools/githunter/_types.py
bond/tools/githunter/tools.py
bond/tools/memory/__init__.py
bond/tools/memory/_models.py
bond/tools/memory/_protocols.py
bond/tools/memory/tools.py
bond/tools/memory/backends/__init__.py
bond/tools/memory/backends/pgvector.py
bond/tools/memory/backends/qdrant.py
bond/tools/schema/__init__.py
bond/tools/schema/_models.py
bond/tools/schema/_protocols.py
bond/tools/schema/tools.py
bond/trace/__init__.py
bond/trace/_models.py
bond/trace/_protocols.py
bond/trace/capture.py
bond/trace/replay.py
bond/trace/backends/__init__.py
bond/trace/backends/json_file.py
bond_agent-0.1.2.dist-info/METADATA
bond_agent-0.1.2.dist-info/WHEEL
bond_agent-0.1.2.dist-info/licenses/LICENSE
bond_agent-0.1.2.dist-info/RECORD
